hydrotoolbox/__init__.py
hydrotoolbox/baseflow_sep.py
hydrotoolbox/hydrotoolbox.py
hydrotoolbox/utils.py
hydrotoolbox/baseflow/__init__.py
hydrotoolbox/baseflow/comparison.py
hydrotoolbox/baseflow/example.csv
hydrotoolbox/baseflow/param_estimate.py
hydrotoolbox/baseflow/separation.py
hydrotoolbox/baseflow/utils.py
hydrotoolbox/baseflow/methods/__init__.py
hydrotoolbox/baseflow/methods/boughton.py
hydrotoolbox/baseflow/methods/chapman.py
hydrotoolbox/baseflow/methods/cm.py
hydrotoolbox/baseflow/methods/eckhardt.py
hydrotoolbox/baseflow/methods/ewma.py
hydrotoolbox/baseflow/methods/five_day.py
hydrotoolbox/baseflow/methods/fixed.py
hydrotoolbox/baseflow/methods/furey.py
hydrotoolbox/baseflow/methods/ihacres.py
hydrotoolbox/baseflow/methods/lh.py
hydrotoolbox/baseflow/methods/local.py
hydrotoolbox/baseflow/methods/slide.py
hydrotoolbox/baseflow/methods/strict.py
hydrotoolbox/baseflow/methods/ukih.py
hydrotoolbox/baseflow/methods/willems.py
hydrotoolbox/indices/indices.py
hydrotoolbox/toolbox_utils/docs/conf.py
hydrotoolbox/toolbox_utils/src/toolbox_utils/__init__.py
hydrotoolbox/toolbox_utils/src/toolbox_utils/tsutils.py
hydrotoolbox/toolbox_utils/src/toolbox_utils/readers/__init__.py
hydrotoolbox/toolbox_utils/src/toolbox_utils/readers/hbn.py
hydrotoolbox/toolbox_utils/src/toolbox_utils/readers/plotgen.py
hydrotoolbox/toolbox_utils/src/toolbox_utils/readers/wdm.py
hydrotoolbox/toolbox_utils/tests/test_asbestfreq.py
hydrotoolbox/toolbox_utils/tests/test_date_slice.py
hydrotoolbox/toolbox_utils/tests/test_dateparse.py
hydrotoolbox/toolbox_utils/tests/test_extract.py
hydrotoolbox/toolbox_utils/tests/test_hbn.py
hydrotoolbox/toolbox_utils/tests/test_make_list.py
hydrotoolbox/toolbox_utils/tests/test_period_timestamp.py
hydrotoolbox/toolbox_utils/tests/test_plotgen.py
hydrotoolbox/toolbox_utils/tests/test_range_to_numlist.py
hydrotoolbox/toolbox_utils/tests/test_read.py
hydrotoolbox/toolbox_utils/tests/test_wdm.py
hydrotoolbox-2.0.14.dist-info/licenses/LICENSE.txt
hydrotoolbox-2.0.14.dist-info/METADATA
hydrotoolbox-2.0.14.dist-info/WHEEL
hydrotoolbox-2.0.14.dist-info/entry_points.txt
hydrotoolbox-2.0.14.dist-info/top_level.txt
hydrotoolbox-2.0.14.dist-info/RECORD
